dedupmarcxml/__init__.py
dedupmarcxml/briefrecord.py
dedupmarcxml/evaluate.py
dedupmarcxml/tools.py
dedupmarcxml/version.py
dedupmarcxml/data/editions_data.pickle
dedupmarcxml/data/mlp_classifier_book_model.pickle
dedupmarcxml/data/publishers_data.pickle
dedupmarcxml/data/randomforest_book_model.pickle
dedupmarcxml/data/randomforest_general_model.pickle
dedupmarcxml/data/randomforest_music_model.pickle
dedupmarcxml/score/__init__.py
dedupmarcxml/score/editions.py
dedupmarcxml/score/extent.py
dedupmarcxml/score/methods.py
dedupmarcxml/score/names.py
dedupmarcxml/score/publishers.py
dedupmarcxml-1.1.4.dist-info/licenses/license.txt
dedupmarcxml-1.1.4.dist-info/METADATA
dedupmarcxml-1.1.4.dist-info/WHEEL
dedupmarcxml-1.1.4.dist-info/top_level.txt
dedupmarcxml-1.1.4.dist-info/RECORD
