Metadata-Version: 2.4
Name: dedupmarcxml
Version: 1.1.4
Summary: This python module is a tool to dedup MarcXML records.
Author-email: Raphaël Rey <raphael.rey@slsp.ch>
Project-URL: Homepage, https://github.com/Swiss-Library-Service-Platform/dedupmarcxml
Project-URL: Bug Tracker, https://github.com/Swiss-Library-Service-Platform/dedupmarcxml/issues
Classifier: Programming Language :: Python :: 3
Classifier: License :: OSI Approved :: GNU General Public License v3 (GPLv3)
Classifier: Operating System :: OS Independent
Requires-Python: >=3.9
License-File: license.txt
Requires-Dist: lxml
Requires-Dist: numpy
Requires-Dist: Levenshtein
Dynamic: license-file
